jaraco/services/__init__.py
jaraco/services/paths.py
jaraco.services-4.0.0.dist-info/LICENSE
jaraco.services-4.0.0.dist-info/METADATA
jaraco.services-4.0.0.dist-info/WHEEL
jaraco.services-4.0.0.dist-info/top_level.txt
jaraco.services-4.0.0.dist-info/RECORD
